cohesion_tools/__init__.py
cohesion_tools/evaluators/__init__.py
cohesion_tools/evaluators/bridging.py
cohesion_tools/evaluators/cohesion.py
cohesion_tools/evaluators/coreference.py
cohesion_tools/evaluators/pas.py
cohesion_tools/evaluators/utils.py
cohesion_tools/extractors/__init__.py
cohesion_tools/extractors/base.py
cohesion_tools/extractors/bridging.py
cohesion_tools/extractors/coreference.py
cohesion_tools/extractors/pas.py
cohesion_tools/py.typed
cohesion_tools/task.py
cohesion_tools-0.7.6.dist-info/WHEEL
cohesion_tools-0.7.6.dist-info/METADATA
cohesion_tools-0.7.6.dist-info/RECORD
