Metadata-Version: 2.4
Name: cohesion-tools
Version: 0.7.6
Summary: A preprocessing and evaluation tools for Japanese cohesion analysis
Keywords: NLP,Japanese
Author: Nobuhiro Ueda
Author-email: Nobuhiro Ueda <ueda-n127@hotmail.co.jp>
License-Expression: MIT
Classifier: License :: OSI Approved :: MIT License
Classifier: Natural Language :: Japanese
Classifier: Operating System :: MacOS
Classifier: Operating System :: MacOS :: MacOS X
Classifier: Operating System :: Microsoft :: Windows
Classifier: Operating System :: POSIX :: Linux
Classifier: Programming Language :: Python :: 3
Classifier: Programming Language :: Python :: 3.9
Classifier: Programming Language :: Python :: 3.10
Classifier: Programming Language :: Python :: 3.11
Classifier: Programming Language :: Python :: 3.12
Classifier: Programming Language :: Python :: 3.13
Classifier: Programming Language :: Python :: 3.14
Classifier: Topic :: Scientific/Engineering
Classifier: Topic :: Software Development :: Libraries
Classifier: Topic :: Software Development :: Libraries :: Python Modules
Classifier: Topic :: Text Processing
Classifier: Topic :: Text Processing :: Linguistic
Requires-Dist: rhoknp>=1.5.1
Requires-Dist: pandas>=2.3.0,<2.4.0 ; extra == 'eval'
Maintainer: Nobuhiro Ueda
Maintainer-email: Nobuhiro Ueda <ueda-n127@hotmail.co.jp>
Requires-Python: >=3.9
Provides-Extra: eval
